libertai_client/__init__.py
libertai_client/__main__.py
libertai_client/commands/agent.py
libertai_client/config.py
libertai_client/interfaces/agent.py
libertai_client/main.py
libertai_client/utils/__init__.py
libertai_client/utils/agent.py
libertai_client/utils/system.py
libertai_client/utils/typer.py
libertai_client-0.2.0.dist-info/METADATA
libertai_client-0.2.0.dist-info/WHEEL
libertai_client-0.2.0.dist-info/entry_points.txt
libertai_client-0.2.0.dist-info/RECORD
