Metadata-Version: 2.3
Name: libertai-client
Version: 0.2.0
Summary: CLI for LibertAI products
Author: LibertAI.io team
Author-email: hello@libertai.io
Requires-Python: >=3.11,<4.0
Classifier: Development Status :: 2 - Pre-Alpha
Classifier: Intended Audience :: Developers
Classifier: Operating System :: OS Independent
Classifier: Programming Language :: Python :: 3
Classifier: Programming Language :: Python :: 3.11
Classifier: Programming Language :: Python :: 3.12
Classifier: Programming Language :: Python :: 3.13
Classifier: Topic :: Scientific/Engineering :: Artificial Intelligence
Requires-Dist: aiohttp (>=3.12.14,<4.0.0)
Requires-Dist: paramiko (>=3.5.1,<4.0.0)
Requires-Dist: pathspec (>=0.12.1,<0.13.0)
Requires-Dist: pydantic (>=2.11.7,<3.0.0)
Requires-Dist: python-dotenv (>=1.0.1,<2.0.0)
Requires-Dist: typer (>=0.12.5,<0.13.0)
Project-URL: Documentation, https://docs.libertai.io
Project-URL: Homepage, https://libertai.io
Project-URL: Repository, https://github.com/LibertAI/libertai-client
